{
  "name" : "j3021_6",
  "type" : "RCPSP",
  "activities" : [ {
    "id" : 0,
    "duration" : 0,
    "resourceConsumption" : [ 0, 0, 0, 0 ],
    "successors" : [ 1, 2, 3 ]
  }, {
    "id" : 1,
    "duration" : 1,
    "resourceConsumption" : [ 0, 5, 7, 7 ],
    "successors" : [ 9, 10, 14 ]
  }, {
    "id" : 2,
    "duration" : 9,
    "resourceConsumption" : [ 0, 8, 5, 4 ],
    "successors" : [ 4, 7, 11 ]
  }, {
    "id" : 3,
    "duration" : 5,
    "resourceConsumption" : [ 0, 10, 0, 8 ],
    "successors" : [ 18 ]
  }, {
    "id" : 4,
    "duration" : 6,
    "resourceConsumption" : [ 0, 6, 10, 2 ],
    "successors" : [ 5, 6, 8 ]
  }, {
    "id" : 5,
    "duration" : 4,
    "resourceConsumption" : [ 2, 0, 0, 10 ],
    "successors" : [ 13, 19, 27 ]
  }, {
    "id" : 6,
    "duration" : 9,
    "resourceConsumption" : [ 5, 0, 4, 0 ],
    "successors" : [ 12, 15, 29 ]
  }, {
    "id" : 7,
    "duration" : 7,
    "resourceConsumption" : [ 0, 0, 7, 0 ],
    "successors" : [ 21 ]
  }, {
    "id" : 8,
    "duration" : 4,
    "resourceConsumption" : [ 0, 0, 10, 0 ],
    "successors" : [ 10, 16, 25 ]
  }, {
    "id" : 9,
    "duration" : 8,
    "resourceConsumption" : [ 0, 1, 0, 0 ],
    "successors" : [ 11, 17 ]
  }, {
    "id" : 10,
    "duration" : 10,
    "resourceConsumption" : [ 2, 0, 0, 8 ],
    "successors" : [ 22 ]
  }, {
    "id" : 11,
    "duration" : 4,
    "resourceConsumption" : [ 2, 0, 0, 0 ],
    "successors" : [ 25 ]
  }, {
    "id" : 12,
    "duration" : 10,
    "resourceConsumption" : [ 0, 7, 5, 0 ],
    "successors" : [ 18, 21, 23 ]
  }, {
    "id" : 13,
    "duration" : 2,
    "resourceConsumption" : [ 9, 0, 0, 0 ],
    "successors" : [ 20, 26 ]
  }, {
    "id" : 14,
    "duration" : 8,
    "resourceConsumption" : [ 0, 7, 0, 1 ],
    "successors" : [ 15, 16, 24 ]
  }, {
    "id" : 15,
    "duration" : 9,
    "resourceConsumption" : [ 0, 5, 0, 0 ],
    "successors" : [ 18, 22, 28 ]
  }, {
    "id" : 16,
    "duration" : 10,
    "resourceConsumption" : [ 0, 10, 0, 7 ],
    "successors" : [ 21, 27, 28 ]
  }, {
    "id" : 17,
    "duration" : 3,
    "resourceConsumption" : [ 8, 2, 0, 0 ],
    "successors" : [ 19, 20 ]
  }, {
    "id" : 18,
    "duration" : 10,
    "resourceConsumption" : [ 10, 6, 0, 6 ],
    "successors" : [ 30 ]
  }, {
    "id" : 19,
    "duration" : 4,
    "resourceConsumption" : [ 0, 0, 0, 8 ],
    "successors" : [ 23, 24 ]
  }, {
    "id" : 20,
    "duration" : 5,
    "resourceConsumption" : [ 0, 2, 4, 0 ],
    "successors" : [ 24 ]
  }, {
    "id" : 21,
    "duration" : 3,
    "resourceConsumption" : [ 0, 0, 6, 0 ],
    "successors" : [ 22 ]
  }, {
    "id" : 22,
    "duration" : 6,
    "resourceConsumption" : [ 5, 3, 8, 0 ],
    "successors" : [ 30 ]
  }, {
    "id" : 23,
    "duration" : 5,
    "resourceConsumption" : [ 7, 1, 8, 0 ],
    "successors" : [ 25 ]
  }, {
    "id" : 24,
    "duration" : 6,
    "resourceConsumption" : [ 0, 6, 7, 6 ],
    "successors" : [ 29 ]
  }, {
    "id" : 25,
    "duration" : 4,
    "resourceConsumption" : [ 0, 0, 0, 10 ],
    "successors" : [ 26 ]
  }, {
    "id" : 26,
    "duration" : 4,
    "resourceConsumption" : [ 9, 0, 1, 0 ],
    "successors" : [ 28, 30 ]
  }, {
    "id" : 27,
    "duration" : 4,
    "resourceConsumption" : [ 0, 8, 9, 1 ],
    "successors" : [ 29 ]
  }, {
    "id" : 28,
    "duration" : 5,
    "resourceConsumption" : [ 0, 0, 3, 0 ],
    "successors" : [ 31 ]
  }, {
    "id" : 29,
    "duration" : 3,
    "resourceConsumption" : [ 7, 10, 9, 1 ],
    "successors" : [ 31 ]
  }, {
    "id" : 30,
    "duration" : 6,
    "resourceConsumption" : [ 9, 0, 5, 5 ],
    "successors" : [ 31 ]
  }, {
    "id" : 31,
    "duration" : 0,
    "resourceConsumption" : [ 0, 0, 0, 0 ],
    "successors" : [ ]
  } ],
  "resourcesAvailabilities" : [ 13, 14, 13, 13 ],
  "horizon" : 174,
  "size" : 32
}